<?xml version="1.0" encoding="UTF-8"?>
<beans xmlns="http://www.springframework.org/schema/beans"
       xmlns:xsi="http://www.w3.org/2001/XMLSchema-instance"
       xmlns:context="http://www.springframework.org/schema/context"
       xsi:schemaLocation="http://www.springframework.org/schema/beans
           http://www.springframework.org/schema/beans/spring-beans-3.0.xsd
           http://www.springframework.org/schema/context
           http://www.springframework.org/schema/context/spring-context-3.1.xsd">
   <context:property-placeholder location="config/spymemcached.properties" ignore-unresolvable="true"/>
       <bean id="memcachedClient" class="com.ty.erp.services.common.cache.CustomerMemcachedClientFactoryBean">
           <property name="servers" value="${memcache.spymemcacheServers}" />
           <!--<property name="protocol" value="BINARY"/>-->
           <!--<property name="transcoder">-->
               <!--<bean class="net.spy.memcached.transcoders.SerializingTranscoder">-->
                   <!--<property name="compressionThreshold" value="1024"/>-->
               <!--</bean>-->
           <!--</property>-->
           <!--&lt;!&ndash;<property name="opTimeout" value="1000"/>&ndash;&gt;-->
           <!--<property name="daemon" value="true"></property>-->
           <!--<property name="timeoutExceptionThreshold" value="1998"/>-->
           <!--&lt;!&ndash; <property name="hashAlg" value="KETAMA_HASH"/> &ndash;&gt;-->
           <!--<property name="locatorType" value="CONSISTENT"/>-->
           <!--<property name="failureMode" value="Redistribute"/>-->
           <!--<property name="useNagleAlgorithm" value="false"/>-->
       </bean>
       <bean id="customerSpyMemcached" class="com.ty.erp.services.common.cache.CustomerSpyMemcached">
           <property name="debug" value="false"></property>
       </bean>
</beans>